timespent.py
git_timespent-0.1.0.dist-info/licenses/LICENSE
git_timespent-0.1.0.dist-info/METADATA
git_timespent-0.1.0.dist-info/WHEEL
git_timespent-0.1.0.dist-info/entry_points.txt
git_timespent-0.1.0.dist-info/top_level.txt
git_timespent-0.1.0.dist-info/RECORD
