Metadata-Version: 2.4
Name: git-timespent
Version: 0.1.0
Summary: Estimate worked hours per author in a git repository.
Author: Giovanni Paolo
Requires-Python: >=3.6
License-File: LICENSE
Dynamic: license-file
